<?xml version="1.0" encoding="utf-8"?>
<doctrine-mapping xmlns="http://doctrine-project.org/schemas/orm/doctrine-mapping" xmlns:xsi="http://www.w3.org/2001/XMLSchema-instance" xsi:schemaLocation="http://doctrine-project.org/schemas/orm/doctrine-mapping https://www.doctrine-project.org/schemas/orm/doctrine-mapping.xsd">
  <entity name="annotation\PasswordResets" table="password_resets">
    <indexes>
      <index name="password_resets_email_index" columns="email"/>
    </indexes>
    <id name="id" type="integer" column="id">
      <generator strategy="IDENTITY"/>
    </id>
    <field name="email" type="string" column="email" length="255" nullable="false">
      <options>
        <option name="fixed"/>
      </options>
    </field>
    <field name="token" type="string" column="token" length="255" nullable="false">
      <options>
        <option name="fixed"/>
      </options>
    </field>
    <field name="createdAt" type="datetime" column="created_at" nullable="true"/>
  </entity>
</doctrine-mapping>
